<Properties StartupConfiguration="{A1EF6EF3-F138-4B81-8B83-80B8767F6B73}|Default">
  <MonoDevelop.Ide.Workbench>
    <Pads>
      <Pad Id="ProjectPad">
        <State name="__root__">
          <Node name="BOOKcheck" expanded="True">
            <Node name="BOOKcheck" expanded="True">
              <Node name="Controllers" expanded="True">
                <Node name="BookController.cs" selected="True" />
              </Node>
              <Node name="Managers" expanded="True">
                <Node name="Book" expanded="True" />
                <Node name="Liber" expanded="True" />
              </Node>
              <Node name="Migrations" expanded="True">
                <Node name="20210416200349_InitialCreate.cs" expanded="True" />
                <Node name="20210420235654_Libb.cs" expanded="True" />
              </Node>
              <Node name="Storage" expanded="True">
                <Node name="Entity" expanded="True" />
                <Node name="Lib" expanded="True" />
                <Node name="User" expanded="True" />
              </Node>
            </Node>
          </Node>
        </State>
      </Pad>
    </Pads>
  </MonoDevelop.Ide.Workbench>
  <MonoDevelop.Ide.DebuggingService.PinnedWatches />
  <MonoDevelop.Ide.ItemProperties.BOOKcheck PreferredExecutionTarget="/Applications/Safari.app" />
  <MonoDevelop.Ide.Workspace ActiveConfiguration="Debug" />
  <MonoDevelop.Ide.DebuggingService.Breakpoints>
    <BreakpointStore />
  </MonoDevelop.Ide.DebuggingService.Breakpoints>
  <MultiItemStartupConfigurations />
</Properties>